zfnlib/__init__.py
zfnlib-0.1.dist-info/METADATA
zfnlib-0.1.dist-info/WHEEL
zfnlib-0.1.dist-info/top_level.txt
zfnlib-0.1.dist-info/RECORD
