Metadata-Version: 2.1
Name: zfnlib
Version: 0.1
Summary: My lib
Author-email: zfn <z@zhufn.fun>
Classifier: License :: OSI Approved :: GNU General Public License v3 (GPLv3)
Requires-Python: >=3.8
Requires-Dist: pwntools
Requires-Dist: pipe
